MANIFEST.in
README.md
requirements.txt
setup.py
hik_camera/MvCameraNode-CH.csv
hik_camera/__info__.py
hik_camera/__init__.py
hik_camera/bandwidth.py
hik_camera/collect_img.py
hik_camera/get_all_ips.py
hik_camera/hik_camera.py
hik_camera/tmp_windows_debug.py
hik_camera.egg-info/PKG-INFO
hik_camera.egg-info/SOURCES.txt
hik_camera.egg-info/dependency_links.txt
hik_camera.egg-info/requires.txt
hik_camera.egg-info/top_level.txt
test/test_base.py
test/test_continuous_adjust_exposure.py
test/test_raw.py